<?xml version="1.0" encoding="utf-8"?>
<!DOCTYPE hibernate-mapping PUBLIC "-//Hibernate/Hibernate Mapping DTD 3.0//EN"
"http://hibernate.sourceforge.net/hibernate-mapping-3.0.dtd">
<!-- 
    Mapping file autogenerated by MyEclipse Persistence Tools
-->
<hibernate-mapping>
    <class name="sdaac.wym.app.entity.vave.PointsDetails" table="VAVE_PointsDetails" schema="dbo" catalog="EPR">
        <id name="id" type="java.lang.Integer">
            <column name="id" />
            <generator class="native"></generator>
        </id>
        <property name="uid" type="java.lang.String">
            <column name="uid" length="50" not-null="true" />
        </property>
        <property name="totalSaving" type="double">
            <column name="total_saving" precision="18" scale="0" />
        </property>
        <property name="year" type="java.lang.Integer">
            <column name="_year" />
        </property>
    </class>
</hibernate-mapping>
