<?xml version="1.0" encoding="utf-8"?>
<!DOCTYPE hibernate-mapping PUBLIC "-//Hibernate/Hibernate Mapping DTD 3.0//EN"
"http://hibernate.sourceforge.net/hibernate-mapping-3.0.dtd">
<!-- 
    Mapping file autogenerated by MyEclipse Persistence Tools
-->
<hibernate-mapping>
    <class name="sdaac.wym.app.Service.SAP.SapBom" table="BOM" schema="dbo" catalog="EPR">
        
     	<id name="id" type="java.lang.Integer">
			<column name="id" />
			<generator class="native" />
		</id>

            <property name="assembly" type="java.lang.String">
                <column name="Assembly" />
            </property>
          
            <property name="component" type="java.lang.String">
                <column name="Component" />
            </property>
            
            <property name="CompQty_UoM" type="java.lang.Float">
                <column name="CompQty_AltUoM" precision="53" scale="0" />
            </property>
			 <property name="AltUoM" type="java.lang.String">
                <column name="AltUom" precision="53" scale="0" />
            </property>
            <property name="base_Unit" type="java.lang.String">
                <column name="Base_Unit" precision="53" scale="0" />
            </property>
			 <property name="comp_Quantity" type="java.lang.Float">
                <column name="Comp_Quantity" precision="53" scale="0" />
            </property>
 
            <property name="validate_time" type="java.util.Date">
                <column name="`Valid_from`" length="23" />
            </property>


    </class>
</hibernate-mapping>
